cythonlookupdicts/README.MD
cythonlookupdicts/__init__.py
cythonlookupdicts/lookdicy.pyx
cythonlookupdicts/requirements.txt
cythonlookupdicts/thirdparty.json
cythonlookupdicts-0.10.dist-info/LICENSE.rst
cythonlookupdicts-0.10.dist-info/METADATA
cythonlookupdicts-0.10.dist-info/WHEEL
cythonlookupdicts-0.10.dist-info/top_level.txt
cythonlookupdicts-0.10.dist-info/RECORD
