Metadata-Version: 2.1
Name: cythonlookupdicts
Version: 0.10
Summary: Insanely fast Cython lookup dicts for tedious datatypes (useful for Sports betting)
Home-page: https://github.com/hansalemaos/cythonlookupdicts
Author: Johannes Fischer
Author-email: aulasparticularesdealemaosp@gmail.com
License: MIT
Keywords: numpy,C,cython
Classifier: Development Status :: 4 - Beta
Classifier: Programming Language :: Python :: 3 :: Only
Classifier: Programming Language :: Python :: 3.10
Classifier: Topic :: Software Development :: Libraries :: Python Modules
Classifier: Topic :: Utilities
License-File: LICENSE.rst
Requires-Dist: cycompi
Requires-Dist: numpy
